{
  "id": "level_072",
  "titleKey": "level.072.title",
  "objectiveKey": "objective.advanced",
  "width": 12,
  "height": 12,
  "difficulty": 38,
  "recommendedMoves": 73,
  "generatedSeed": 3576680480,
  "pen": {
    "x": 5.5,
    "y": -1.25,
    "entryDirection": "south"
  },
  "sheep": [
    {
      "id": "s001",
      "x": 1,
      "y": 6,
      "facing": "south",
      "color": "yellow"
    },
    {
      "id": "s002",
      "x": 4,
      "y": 1,
      "facing": "north",
      "color": "blue"
    },
    {
      "id": "s003",
      "x": 7,
      "y": 10,
      "facing": "south",
      "color": "pink"
    },
    {
      "id": "s004",
      "x": 6,
      "y": 3,
      "facing": "north",
      "color": "mint"
    },
    {
      "id": "s005",
      "x": 8,
      "y": 2,
      "facing": "north",
      "color": "blue"
    },
    {
      "id": "s006",
      "x": 2,
      "y": 5,
      "facing": "north",
      "color": "cream"
    },
    {
      "id": "s007",
      "x": 7,
      "y": 8,
      "facing": "south",
      "color": "blue"
    },
    {
      "id": "s008",
      "x": 5,
      "y": 9,
      "facing": "south",
      "color": "cream"
    },
    {
      "id": "s009",
      "x": 10,
      "y": 1,
      "facing": "north",
      "color": "cream"
    },
    {
      "id": "s010",
      "x": 4,
      "y": 5,
      "facing": "north",
      "color": "mint"
    },
    {
      "id": "s011",
      "x": 4,
      "y": 0,
      "facing": "north",
      "color": "mint"
    },
    {
      "id": "s012",
      "x": 1,
      "y": 11,
      "facing": "south",
      "color": "yellow"
    },
    {
      "id": "s013",
      "x": 10,
      "y": 2,
      "facing": "north",
      "color": "pink"
    },
    {
      "id": "s014",
      "x": 6,
      "y": 5,
      "facing": "north",
      "color": "yellow"
    },
    {
      "id": "s015",
      "x": 7,
      "y": 7,
      "facing": "south",
      "color": "yellow"
    },
    {
      "id": "s016",
      "x": 4,
      "y": 2,
      "facing": "north",
      "color": "yellow"
    },
    {
      "id": "s017",
      "x": 0,
      "y": 3,
      "facing": "north",
      "color": "pink"
    },
    {
      "id": "s018",
      "x": 5,
      "y": 7,
      "facing": "south",
      "color": "mint"
    },
    {
      "id": "s019",
      "x": 2,
      "y": 3,
      "facing": "north",
      "color": "blue"
    },
    {
      "id": "s020",
      "x": 5,
      "y": 8,
      "facing": "south",
      "color": "pink"
    },
    {
      "id": "s021",
      "x": 2,
      "y": 4,
      "facing": "north",
      "color": "yellow"
    },
    {
      "id": "s022",
      "x": 2,
      "y": 0,
      "facing": "north",
      "color": "cream"
    },
    {
      "id": "s023",
      "x": 11,
      "y": 8,
      "facing": "south",
      "color": "blue"
    },
    {
      "id": "s024",
      "x": 9,
      "y": 11,
      "facing": "south",
      "color": "blue"
    },
    {
      "id": "s025",
      "x": 4,
      "y": 4,
      "facing": "north",
      "color": "pink"
    },
    {
      "id": "s026",
      "x": 1,
      "y": 10,
      "facing": "south",
      "color": "cream"
    },
    {
      "id": "s027",
      "x": 11,
      "y": 6,
      "facing": "south",
      "color": "cream"
    },
    {
      "id": "s028",
      "x": 9,
      "y": 10,
      "facing": "south",
      "color": "yellow"
    },
    {
      "id": "s029",
      "x": 3,
      "y": 9,
      "facing": "south",
      "color": "blue"
    },
    {
      "id": "s030",
      "x": 5,
      "y": 10,
      "facing": "south",
      "color": "yellow"
    },
    {
      "id": "s031",
      "x": 8,
      "y": 0,
      "facing": "north",
      "color": "pink"
    },
    {
      "id": "s032",
      "x": 1,
      "y": 7,
      "facing": "south",
      "color": "blue"
    },
    {
      "id": "s033",
      "x": 2,
      "y": 1,
      "facing": "north",
      "color": "pink"
    },
    {
      "id": "s034",
      "x": 2,
      "y": 2,
      "facing": "north",
      "color": "mint"
    },
    {
      "id": "s035",
      "x": 8,
      "y": 1,
      "facing": "north",
      "color": "mint"
    },
    {
      "id": "s036",
      "x": 1,
      "y": 9,
      "facing": "south",
      "color": "pink"
    },
    {
      "id": "s037",
      "x": 3,
      "y": 10,
      "facing": "south",
      "color": "mint"
    },
    {
      "id": "s038",
      "x": 9,
      "y": 7,
      "facing": "south",
      "color": "mint"
    },
    {
      "id": "s039",
      "x": 11,
      "y": 7,
      "facing": "south",
      "color": "yellow"
    },
    {
      "id": "s040",
      "x": 6,
      "y": 2,
      "facing": "north",
      "color": "pink"
    },
    {
      "id": "s041",
      "x": 11,
      "y": 10,
      "facing": "south",
      "color": "pink"
    },
    {
      "id": "s042",
      "x": 10,
      "y": 0,
      "facing": "north",
      "color": "yellow"
    },
    {
      "id": "s043",
      "x": 8,
      "y": 6,
      "facing": "north",
      "color": "mint"
    },
    {
      "id": "s044",
      "x": 3,
      "y": 11,
      "facing": "south",
      "color": "pink"
    },
    {
      "id": "s045",
      "x": 4,
      "y": 3,
      "facing": "north",
      "color": "cream"
    },
    {
      "id": "s046",
      "x": 3,
      "y": 6,
      "facing": "south",
      "color": "pink"
    },
    {
      "id": "s047",
      "x": 3,
      "y": 7,
      "facing": "south",
      "color": "cream"
    },
    {
      "id": "s048",
      "x": 8,
      "y": 4,
      "facing": "north",
      "color": "cream"
    },
    {
      "id": "s049",
      "x": 7,
      "y": 6,
      "facing": "south",
      "color": "cream"
    },
    {
      "id": "s050",
      "x": 0,
      "y": 4,
      "facing": "north",
      "color": "mint"
    },
    {
      "id": "s051",
      "x": 9,
      "y": 6,
      "facing": "south",
      "color": "blue"
    },
    {
      "id": "s052",
      "x": 1,
      "y": 8,
      "facing": "south",
      "color": "mint"
    },
    {
      "id": "s053",
      "x": 8,
      "y": 3,
      "facing": "north",
      "color": "yellow"
    },
    {
      "id": "s054",
      "x": 10,
      "y": 3,
      "facing": "north",
      "color": "mint"
    },
    {
      "id": "s055",
      "x": 10,
      "y": 4,
      "facing": "north",
      "color": "blue"
    },
    {
      "id": "s056",
      "x": 6,
      "y": 1,
      "facing": "north",
      "color": "cream"
    },
    {
      "id": "s057",
      "x": 7,
      "y": 9,
      "facing": "south",
      "color": "mint"
    },
    {
      "id": "s058",
      "x": 6,
      "y": 0,
      "facing": "north",
      "color": "yellow"
    },
    {
      "id": "s059",
      "x": 0,
      "y": 2,
      "facing": "north",
      "color": "cream"
    },
    {
      "id": "s060",
      "x": 3,
      "y": 8,
      "facing": "south",
      "color": "yellow"
    },
    {
      "id": "s061",
      "x": 5,
      "y": 11,
      "facing": "south",
      "color": "blue"
    },
    {
      "id": "s062",
      "x": 11,
      "y": 11,
      "facing": "south",
      "color": "cream"
    },
    {
      "id": "s063",
      "x": 8,
      "y": 5,
      "facing": "north",
      "color": "pink"
    },
    {
      "id": "s064",
      "x": 0,
      "y": 0,
      "facing": "north",
      "color": "blue"
    },
    {
      "id": "s065",
      "x": 0,
      "y": 5,
      "facing": "north",
      "color": "blue"
    },
    {
      "id": "s066",
      "x": 11,
      "y": 9,
      "facing": "south",
      "color": "mint"
    },
    {
      "id": "s067",
      "x": 9,
      "y": 9,
      "facing": "south",
      "color": "cream"
    },
    {
      "id": "s068",
      "x": 5,
      "y": 6,
      "facing": "south",
      "color": "blue"
    },
    {
      "id": "s069",
      "x": 6,
      "y": 4,
      "facing": "north",
      "color": "blue"
    },
    {
      "id": "s070",
      "x": 7,
      "y": 11,
      "facing": "south",
      "color": "cream"
    },
    {
      "id": "s071",
      "x": 9,
      "y": 8,
      "facing": "south",
      "color": "pink"
    },
    {
      "id": "s072",
      "x": 0,
      "y": 1,
      "facing": "north",
      "color": "yellow"
    },
    {
      "id": "s073",
      "x": 10,
      "y": 5,
      "facing": "north",
      "color": "yellow"
    }
  ],
  "obstacles": [
    {
      "x": 8,
      "y": 10,
      "kind": "flower"
    },
    {
      "x": 4,
      "y": 7,
      "kind": "flower"
    },
    {
      "x": 9,
      "y": 5,
      "kind": "fence"
    },
    {
      "x": 11,
      "y": 4,
      "kind": "fence"
    },
    {
      "x": 9,
      "y": 3,
      "kind": "fence"
    },
    {
      "x": 6,
      "y": 7,
      "kind": "fence"
    },
    {
      "x": 0,
      "y": 9,
      "kind": "hay"
    },
    {
      "x": 10,
      "y": 9,
      "kind": "fence"
    },
    {
      "x": 1,
      "y": 3,
      "kind": "fence"
    }
  ]
}
