{
  "id": "level_147",
  "titleKey": "level.147.title",
  "objectiveKey": "objective.expert",
  "width": 16,
  "height": 16,
  "difficulty": 73,
  "recommendedMoves": 155,
  "generatedSeed": 1574871648,
  "pen": {
    "x": 7.5,
    "y": -1.25,
    "entryDirection": "south"
  },
  "sheep": [
    {
      "id": "s001",
      "x": 3,
      "y": 2,
      "facing": "west",
      "color": "pink"
    },
    {
      "id": "s002",
      "x": 6,
      "y": 0,
      "facing": "west",
      "color": "yellow"
    },
    {
      "id": "s003",
      "x": 4,
      "y": 6,
      "facing": "west",
      "color": "cream"
    },
    {
      "id": "s004",
      "x": 13,
      "y": 1,
      "facing": "east",
      "color": "cream"
    },
    {
      "id": "s005",
      "x": 8,
      "y": 9,
      "facing": "east",
      "color": "blue"
    },
    {
      "id": "s006",
      "x": 0,
      "y": 4,
      "facing": "west",
      "color": "mint"
    },
    {
      "id": "s007",
      "x": 7,
      "y": 1,
      "facing": "east",
      "color": "pink"
    },
    {
      "id": "s008",
      "x": 4,
      "y": 10,
      "facing": "west",
      "color": "yellow"
    },
    {
      "id": "s009",
      "x": 11,
      "y": 3,
      "facing": "east",
      "color": "pink"
    },
    {
      "id": "s010",
      "x": 7,
      "y": 6,
      "facing": "west",
      "color": "blue"
    },
    {
      "id": "s011",
      "x": 3,
      "y": 12,
      "facing": "west",
      "color": "mint"
    },
    {
      "id": "s012",
      "x": 15,
      "y": 15,
      "facing": "east",
      "color": "blue"
    },
    {
      "id": "s013",
      "x": 1,
      "y": 2,
      "facing": "west",
      "color": "yellow"
    },
    {
      "id": "s014",
      "x": 9,
      "y": 13,
      "facing": "east",
      "color": "cream"
    },
    {
      "id": "s015",
      "x": 6,
      "y": 10,
      "facing": "west",
      "color": "pink"
    },
    {
      "id": "s016",
      "x": 12,
      "y": 3,
      "facing": "east",
      "color": "cream"
    },
    {
      "id": "s017",
      "x": 8,
      "y": 14,
      "facing": "west",
      "color": "pink"
    },
    {
      "id": "s018",
      "x": 7,
      "y": 10,
      "facing": "west",
      "color": "mint"
    },
    {
      "id": "s019",
      "x": 4,
      "y": 14,
      "facing": "west",
      "color": "mint"
    },
    {
      "id": "s020",
      "x": 6,
      "y": 1,
      "facing": "east",
      "color": "mint"
    },
    {
      "id": "s021",
      "x": 2,
      "y": 4,
      "facing": "west",
      "color": "yellow"
    },
    {
      "id": "s022",
      "x": 13,
      "y": 11,
      "facing": "east",
      "color": "pink"
    },
    {
      "id": "s023",
      "x": 5,
      "y": 4,
      "facing": "west",
      "color": "mint"
    },
    {
      "id": "s024",
      "x": 2,
      "y": 6,
      "facing": "west",
      "color": "blue"
    },
    {
      "id": "s025",
      "x": 6,
      "y": 6,
      "facing": "west",
      "color": "mint"
    },
    {
      "id": "s026",
      "x": 7,
      "y": 11,
      "facing": "east",
      "color": "mint"
    },
    {
      "id": "s027",
      "x": 7,
      "y": 14,
      "facing": "west",
      "color": "cream"
    },
    {
      "id": "s028",
      "x": 11,
      "y": 13,
      "facing": "east",
      "color": "blue"
    },
    {
      "id": "s029",
      "x": 13,
      "y": 3,
      "facing": "east",
      "color": "yellow"
    },
    {
      "id": "s030",
      "x": 12,
      "y": 11,
      "facing": "east",
      "color": "mint"
    },
    {
      "id": "s031",
      "x": 4,
      "y": 8,
      "facing": "west",
      "color": "cream"
    },
    {
      "id": "s032",
      "x": 7,
      "y": 4,
      "facing": "west",
      "color": "yellow"
    },
    {
      "id": "s033",
      "x": 6,
      "y": 2,
      "facing": "west",
      "color": "yellow"
    },
    {
      "id": "s034",
      "x": 0,
      "y": 12,
      "facing": "west",
      "color": "yellow"
    },
    {
      "id": "s035",
      "x": 8,
      "y": 4,
      "facing": "west",
      "color": "cream"
    },
    {
      "id": "s036",
      "x": 15,
      "y": 13,
      "facing": "east",
      "color": "yellow"
    },
    {
      "id": "s037",
      "x": 11,
      "y": 11,
      "facing": "east",
      "color": "blue"
    },
    {
      "id": "s038",
      "x": 9,
      "y": 8,
      "facing": "west",
      "color": "cream"
    },
    {
      "id": "s039",
      "x": 7,
      "y": 9,
      "facing": "east",
      "color": "yellow"
    },
    {
      "id": "s040",
      "x": 8,
      "y": 11,
      "facing": "east",
      "color": "pink"
    },
    {
      "id": "s041",
      "x": 13,
      "y": 9,
      "facing": "east",
      "color": "blue"
    },
    {
      "id": "s042",
      "x": 10,
      "y": 5,
      "facing": "east",
      "color": "mint"
    },
    {
      "id": "s043",
      "x": 1,
      "y": 12,
      "facing": "west",
      "color": "cream"
    },
    {
      "id": "s044",
      "x": 3,
      "y": 14,
      "facing": "west",
      "color": "pink"
    },
    {
      "id": "s045",
      "x": 14,
      "y": 1,
      "facing": "east",
      "color": "yellow"
    },
    {
      "id": "s046",
      "x": 11,
      "y": 7,
      "facing": "east",
      "color": "cream"
    },
    {
      "id": "s047",
      "x": 1,
      "y": 14,
      "facing": "west",
      "color": "yellow"
    },
    {
      "id": "s048",
      "x": 15,
      "y": 7,
      "facing": "east",
      "color": "pink"
    },
    {
      "id": "s049",
      "x": 7,
      "y": 13,
      "facing": "east",
      "color": "mint"
    },
    {
      "id": "s050",
      "x": 4,
      "y": 0,
      "facing": "west",
      "color": "mint"
    },
    {
      "id": "s051",
      "x": 7,
      "y": 12,
      "facing": "west",
      "color": "pink"
    },
    {
      "id": "s052",
      "x": 9,
      "y": 9,
      "facing": "east",
      "color": "mint"
    },
    {
      "id": "s053",
      "x": 8,
      "y": 15,
      "facing": "east",
      "color": "cream"
    },
    {
      "id": "s054",
      "x": 13,
      "y": 13,
      "facing": "east",
      "color": "pink"
    },
    {
      "id": "s055",
      "x": 14,
      "y": 5,
      "facing": "east",
      "color": "blue"
    },
    {
      "id": "s056",
      "x": 8,
      "y": 2,
      "facing": "west",
      "color": "pink"
    },
    {
      "id": "s057",
      "x": 10,
      "y": 1,
      "facing": "east",
      "color": "blue"
    },
    {
      "id": "s058",
      "x": 5,
      "y": 6,
      "facing": "west",
      "color": "pink"
    },
    {
      "id": "s059",
      "x": 1,
      "y": 0,
      "facing": "west",
      "color": "yellow"
    },
    {
      "id": "s060",
      "x": 5,
      "y": 8,
      "facing": "west",
      "color": "pink"
    },
    {
      "id": "s061",
      "x": 5,
      "y": 10,
      "facing": "west",
      "color": "cream"
    },
    {
      "id": "s062",
      "x": 4,
      "y": 12,
      "facing": "west",
      "color": "blue"
    },
    {
      "id": "s063",
      "x": 8,
      "y": 5,
      "facing": "east",
      "color": "yellow"
    },
    {
      "id": "s064",
      "x": 6,
      "y": 14,
      "facing": "west",
      "color": "yellow"
    },
    {
      "id": "s065",
      "x": 5,
      "y": 2,
      "facing": "west",
      "color": "blue"
    },
    {
      "id": "s066",
      "x": 10,
      "y": 7,
      "facing": "east",
      "color": "pink"
    },
    {
      "id": "s067",
      "x": 9,
      "y": 3,
      "facing": "east",
      "color": "blue"
    },
    {
      "id": "s068",
      "x": 14,
      "y": 11,
      "facing": "east",
      "color": "cream"
    },
    {
      "id": "s069",
      "x": 9,
      "y": 5,
      "facing": "east",
      "color": "blue"
    },
    {
      "id": "s070",
      "x": 9,
      "y": 12,
      "facing": "west",
      "color": "blue"
    },
    {
      "id": "s071",
      "x": 5,
      "y": 14,
      "facing": "west",
      "color": "blue"
    },
    {
      "id": "s072",
      "x": 1,
      "y": 8,
      "facing": "west",
      "color": "mint"
    },
    {
      "id": "s073",
      "x": 6,
      "y": 15,
      "facing": "east",
      "color": "mint"
    },
    {
      "id": "s074",
      "x": 0,
      "y": 14,
      "facing": "west",
      "color": "blue"
    },
    {
      "id": "s075",
      "x": 14,
      "y": 9,
      "facing": "east",
      "color": "mint"
    },
    {
      "id": "s076",
      "x": 7,
      "y": 5,
      "facing": "east",
      "color": "cream"
    },
    {
      "id": "s077",
      "x": 2,
      "y": 12,
      "facing": "west",
      "color": "pink"
    },
    {
      "id": "s078",
      "x": 8,
      "y": 1,
      "facing": "east",
      "color": "cream"
    },
    {
      "id": "s079",
      "x": 2,
      "y": 2,
      "facing": "west",
      "color": "cream"
    },
    {
      "id": "s080",
      "x": 9,
      "y": 1,
      "facing": "east",
      "color": "yellow"
    },
    {
      "id": "s081",
      "x": 15,
      "y": 3,
      "facing": "east",
      "color": "mint"
    },
    {
      "id": "s082",
      "x": 8,
      "y": 7,
      "facing": "east",
      "color": "blue"
    },
    {
      "id": "s083",
      "x": 10,
      "y": 3,
      "facing": "east",
      "color": "mint"
    },
    {
      "id": "s084",
      "x": 12,
      "y": 15,
      "facing": "east",
      "color": "pink"
    },
    {
      "id": "s085",
      "x": 0,
      "y": 10,
      "facing": "west",
      "color": "cream"
    },
    {
      "id": "s086",
      "x": 7,
      "y": 0,
      "facing": "west",
      "color": "cream"
    },
    {
      "id": "s087",
      "x": 12,
      "y": 5,
      "facing": "east",
      "color": "cream"
    },
    {
      "id": "s088",
      "x": 11,
      "y": 5,
      "facing": "east",
      "color": "pink"
    },
    {
      "id": "s089",
      "x": 9,
      "y": 6,
      "facing": "west",
      "color": "cream"
    },
    {
      "id": "s090",
      "x": 6,
      "y": 8,
      "facing": "west",
      "color": "mint"
    },
    {
      "id": "s091",
      "x": 2,
      "y": 14,
      "facing": "west",
      "color": "cream"
    },
    {
      "id": "s092",
      "x": 10,
      "y": 9,
      "facing": "east",
      "color": "pink"
    },
    {
      "id": "s093",
      "x": 8,
      "y": 6,
      "facing": "west",
      "color": "yellow"
    },
    {
      "id": "s094",
      "x": 9,
      "y": 0,
      "facing": "west",
      "color": "mint"
    },
    {
      "id": "s095",
      "x": 9,
      "y": 14,
      "facing": "west",
      "color": "mint"
    },
    {
      "id": "s096",
      "x": 14,
      "y": 15,
      "facing": "east",
      "color": "yellow"
    },
    {
      "id": "s097",
      "x": 8,
      "y": 8,
      "facing": "west",
      "color": "yellow"
    },
    {
      "id": "s098",
      "x": 9,
      "y": 15,
      "facing": "east",
      "color": "yellow"
    },
    {
      "id": "s099",
      "x": 2,
      "y": 8,
      "facing": "west",
      "color": "blue"
    },
    {
      "id": "s100",
      "x": 3,
      "y": 6,
      "facing": "west",
      "color": "yellow"
    },
    {
      "id": "s101",
      "x": 4,
      "y": 2,
      "facing": "west",
      "color": "mint"
    },
    {
      "id": "s102",
      "x": 11,
      "y": 1,
      "facing": "east",
      "color": "mint"
    },
    {
      "id": "s103",
      "x": 11,
      "y": 9,
      "facing": "east",
      "color": "cream"
    },
    {
      "id": "s104",
      "x": 14,
      "y": 13,
      "facing": "east",
      "color": "cream"
    },
    {
      "id": "s105",
      "x": 1,
      "y": 10,
      "facing": "west",
      "color": "pink"
    },
    {
      "id": "s106",
      "x": 12,
      "y": 9,
      "facing": "east",
      "color": "yellow"
    },
    {
      "id": "s107",
      "x": 7,
      "y": 15,
      "facing": "east",
      "color": "pink"
    },
    {
      "id": "s108",
      "x": 13,
      "y": 15,
      "facing": "east",
      "color": "cream"
    },
    {
      "id": "s109",
      "x": 0,
      "y": 0,
      "facing": "west",
      "color": "blue"
    },
    {
      "id": "s110",
      "x": 6,
      "y": 11,
      "facing": "east",
      "color": "blue"
    },
    {
      "id": "s111",
      "x": 10,
      "y": 11,
      "facing": "east",
      "color": "yellow"
    },
    {
      "id": "s112",
      "x": 1,
      "y": 6,
      "facing": "west",
      "color": "mint"
    },
    {
      "id": "s113",
      "x": 11,
      "y": 15,
      "facing": "east",
      "color": "mint"
    },
    {
      "id": "s114",
      "x": 13,
      "y": 7,
      "facing": "east",
      "color": "blue"
    },
    {
      "id": "s115",
      "x": 8,
      "y": 0,
      "facing": "west",
      "color": "pink"
    },
    {
      "id": "s116",
      "x": 13,
      "y": 5,
      "facing": "east",
      "color": "yellow"
    },
    {
      "id": "s117",
      "x": 1,
      "y": 4,
      "facing": "west",
      "color": "blue"
    },
    {
      "id": "s118",
      "x": 8,
      "y": 13,
      "facing": "east",
      "color": "pink"
    },
    {
      "id": "s119",
      "x": 3,
      "y": 4,
      "facing": "west",
      "color": "cream"
    },
    {
      "id": "s120",
      "x": 12,
      "y": 13,
      "facing": "east",
      "color": "mint"
    },
    {
      "id": "s121",
      "x": 3,
      "y": 8,
      "facing": "west",
      "color": "yellow"
    },
    {
      "id": "s122",
      "x": 15,
      "y": 5,
      "facing": "east",
      "color": "mint"
    },
    {
      "id": "s123",
      "x": 15,
      "y": 1,
      "facing": "east",
      "color": "blue"
    },
    {
      "id": "s124",
      "x": 14,
      "y": 7,
      "facing": "east",
      "color": "mint"
    },
    {
      "id": "s125",
      "x": 8,
      "y": 3,
      "facing": "east",
      "color": "yellow"
    },
    {
      "id": "s126",
      "x": 8,
      "y": 10,
      "facing": "west",
      "color": "blue"
    },
    {
      "id": "s127",
      "x": 12,
      "y": 7,
      "facing": "east",
      "color": "yellow"
    },
    {
      "id": "s128",
      "x": 8,
      "y": 12,
      "facing": "west",
      "color": "mint"
    },
    {
      "id": "s129",
      "x": 4,
      "y": 4,
      "facing": "west",
      "color": "pink"
    },
    {
      "id": "s130",
      "x": 6,
      "y": 7,
      "facing": "east",
      "color": "cream"
    },
    {
      "id": "s131",
      "x": 6,
      "y": 12,
      "facing": "west",
      "color": "cream"
    },
    {
      "id": "s132",
      "x": 0,
      "y": 2,
      "facing": "west",
      "color": "blue"
    },
    {
      "id": "s133",
      "x": 10,
      "y": 15,
      "facing": "east",
      "color": "blue"
    },
    {
      "id": "s134",
      "x": 3,
      "y": 10,
      "facing": "west",
      "color": "blue"
    },
    {
      "id": "s135",
      "x": 12,
      "y": 1,
      "facing": "east",
      "color": "pink"
    },
    {
      "id": "s136",
      "x": 9,
      "y": 4,
      "facing": "west",
      "color": "pink"
    },
    {
      "id": "s137",
      "x": 0,
      "y": 6,
      "facing": "west",
      "color": "pink"
    },
    {
      "id": "s138",
      "x": 7,
      "y": 2,
      "facing": "west",
      "color": "cream"
    },
    {
      "id": "s139",
      "x": 2,
      "y": 10,
      "facing": "west",
      "color": "mint"
    },
    {
      "id": "s140",
      "x": 15,
      "y": 9,
      "facing": "east",
      "color": "pink"
    },
    {
      "id": "s141",
      "x": 3,
      "y": 0,
      "facing": "west",
      "color": "pink"
    },
    {
      "id": "s142",
      "x": 7,
      "y": 7,
      "facing": "east",
      "color": "yellow"
    },
    {
      "id": "s143",
      "x": 0,
      "y": 8,
      "facing": "west",
      "color": "pink"
    },
    {
      "id": "s144",
      "x": 10,
      "y": 13,
      "facing": "east",
      "color": "yellow"
    },
    {
      "id": "s145",
      "x": 7,
      "y": 3,
      "facing": "east",
      "color": "cream"
    },
    {
      "id": "s146",
      "x": 9,
      "y": 7,
      "facing": "east",
      "color": "mint"
    },
    {
      "id": "s147",
      "x": 6,
      "y": 3,
      "facing": "east",
      "color": "pink"
    },
    {
      "id": "s148",
      "x": 9,
      "y": 11,
      "facing": "east",
      "color": "cream"
    },
    {
      "id": "s149",
      "x": 2,
      "y": 0,
      "facing": "west",
      "color": "cream"
    },
    {
      "id": "s150",
      "x": 5,
      "y": 12,
      "facing": "west",
      "color": "yellow"
    },
    {
      "id": "s151",
      "x": 6,
      "y": 4,
      "facing": "west",
      "color": "blue"
    },
    {
      "id": "s152",
      "x": 7,
      "y": 8,
      "facing": "west",
      "color": "blue"
    },
    {
      "id": "s153",
      "x": 14,
      "y": 3,
      "facing": "east",
      "color": "blue"
    },
    {
      "id": "s154",
      "x": 5,
      "y": 0,
      "facing": "west",
      "color": "blue"
    },
    {
      "id": "s155",
      "x": 15,
      "y": 11,
      "facing": "east",
      "color": "yellow"
    }
  ],
  "obstacles": [
    {
      "x": 12,
      "y": 14,
      "kind": "hay"
    },
    {
      "x": 0,
      "y": 9,
      "kind": "tree"
    },
    {
      "x": 1,
      "y": 7,
      "kind": "hay"
    },
    {
      "x": 1,
      "y": 1,
      "kind": "fence"
    },
    {
      "x": 11,
      "y": 10,
      "kind": "flower"
    },
    {
      "x": 2,
      "y": 7,
      "kind": "tree"
    },
    {
      "x": 1,
      "y": 9,
      "kind": "tree"
    },
    {
      "x": 10,
      "y": 0,
      "kind": "fence"
    },
    {
      "x": 13,
      "y": 12,
      "kind": "flower"
    },
    {
      "x": 9,
      "y": 10,
      "kind": "hay"
    },
    {
      "x": 0,
      "y": 5,
      "kind": "fence"
    },
    {
      "x": 13,
      "y": 6,
      "kind": "tree"
    },
    {
      "x": 12,
      "y": 4,
      "kind": "tree"
    },
    {
      "x": 1,
      "y": 5,
      "kind": "flower"
    },
    {
      "x": 14,
      "y": 2,
      "kind": "hay"
    },
    {
      "x": 5,
      "y": 13,
      "kind": "fence"
    },
    {
      "x": 4,
      "y": 9,
      "kind": "flower"
    },
    {
      "x": 12,
      "y": 12,
      "kind": "fence"
    }
  ]
}
