{
  "id": "level_023",
  "titleKey": "level.023.title",
  "objectiveKey": "objective.intermediate",
  "width": 7,
  "height": 7,
  "difficulty": 15,
  "recommendedMoves": 29,
  "generatedSeed": 2344292627,
  "pen": {
    "x": 3,
    "y": -1.25,
    "entryDirection": "south"
  },
  "sheep": [
    {
      "id": "s001",
      "x": 3,
      "y": 1,
      "facing": "east",
      "color": "pink"
    },
    {
      "id": "s002",
      "x": 3,
      "y": 4,
      "facing": "west",
      "color": "yellow"
    },
    {
      "id": "s003",
      "x": 2,
      "y": 6,
      "facing": "west",
      "color": "pink"
    },
    {
      "id": "s004",
      "x": 3,
      "y": 0,
      "facing": "west",
      "color": "mint"
    },
    {
      "id": "s005",
      "x": 2,
      "y": 0,
      "facing": "west",
      "color": "pink"
    },
    {
      "id": "s006",
      "x": 1,
      "y": 6,
      "facing": "west",
      "color": "cream"
    },
    {
      "id": "s007",
      "x": 6,
      "y": 1,
      "facing": "east",
      "color": "blue"
    },
    {
      "id": "s008",
      "x": 5,
      "y": 1,
      "facing": "east",
      "color": "yellow"
    },
    {
      "id": "s009",
      "x": 3,
      "y": 2,
      "facing": "west",
      "color": "cream"
    },
    {
      "id": "s010",
      "x": 6,
      "y": 3,
      "facing": "east",
      "color": "pink"
    },
    {
      "id": "s011",
      "x": 6,
      "y": 5,
      "facing": "east",
      "color": "cream"
    },
    {
      "id": "s012",
      "x": 0,
      "y": 6,
      "facing": "west",
      "color": "yellow"
    },
    {
      "id": "s013",
      "x": 5,
      "y": 3,
      "facing": "east",
      "color": "mint"
    },
    {
      "id": "s014",
      "x": 5,
      "y": 5,
      "facing": "east",
      "color": "pink"
    },
    {
      "id": "s015",
      "x": 2,
      "y": 3,
      "facing": "east",
      "color": "cream"
    },
    {
      "id": "s016",
      "x": 1,
      "y": 2,
      "facing": "west",
      "color": "blue"
    },
    {
      "id": "s017",
      "x": 3,
      "y": 6,
      "facing": "west",
      "color": "mint"
    },
    {
      "id": "s018",
      "x": 0,
      "y": 2,
      "facing": "west",
      "color": "mint"
    },
    {
      "id": "s019",
      "x": 1,
      "y": 0,
      "facing": "west",
      "color": "cream"
    },
    {
      "id": "s020",
      "x": 1,
      "y": 4,
      "facing": "west",
      "color": "mint"
    },
    {
      "id": "s021",
      "x": 4,
      "y": 5,
      "facing": "east",
      "color": "mint"
    },
    {
      "id": "s022",
      "x": 4,
      "y": 3,
      "facing": "east",
      "color": "blue"
    },
    {
      "id": "s023",
      "x": 2,
      "y": 4,
      "facing": "west",
      "color": "blue"
    },
    {
      "id": "s024",
      "x": 0,
      "y": 0,
      "facing": "west",
      "color": "yellow"
    },
    {
      "id": "s025",
      "x": 3,
      "y": 3,
      "facing": "east",
      "color": "yellow"
    },
    {
      "id": "s026",
      "x": 0,
      "y": 4,
      "facing": "west",
      "color": "pink"
    },
    {
      "id": "s027",
      "x": 2,
      "y": 2,
      "facing": "west",
      "color": "yellow"
    },
    {
      "id": "s028",
      "x": 4,
      "y": 1,
      "facing": "east",
      "color": "cream"
    },
    {
      "id": "s029",
      "x": 3,
      "y": 5,
      "facing": "east",
      "color": "blue"
    }
  ],
  "obstacles": [
    {
      "x": 1,
      "y": 5,
      "kind": "hay"
    },
    {
      "x": 5,
      "y": 0,
      "kind": "tree"
    },
    {
      "x": 0,
      "y": 1,
      "kind": "fence"
    },
    {
      "x": 4,
      "y": 4,
      "kind": "flower"
    }
  ]
}
